zu_spider/__init__.py
zu_spider/task.py
zu_spider-0.0.2.dist-info/METADATA
zu_spider-0.0.2.dist-info/WHEEL
zu_spider-0.0.2.dist-info/top_level.txt
zu_spider-0.0.2.dist-info/RECORD
