Metadata-Version: 2.1
Name: zu_spider
Version: 0.0.2
Summary: 爬虫简化程序
Home-page: 
Author: huaqing
Author-email: huaqingshaonian@163.com
Classifier: Programming Language :: Python :: 3
Classifier: License :: OSI Approved :: MIT License
Classifier: Operating System :: OS Independent
